kines/__init__.py
kines/constants.py
kines/date_util.py
kines/decoders.py
kines/kines_cli.py
kines/metrics.py
kines/partition_key_util.py
kines/read_util.py
kines/shard_util.py
kines/stream_util.py
kines/util.py
tests/__init__.py
tests/aws_client_mocks.py
tests/boto3_api_responses.py
tests/test_constants.py
tests/test_kines_cli.py
tests/test_metrics.py
tests/test_read_util.py
tests/test_util.py
kines_proto-1.0.0.dist-info/LICENSE
kines_proto-1.0.0.dist-info/METADATA
kines_proto-1.0.0.dist-info/WHEEL
kines_proto-1.0.0.dist-info/entry_points.txt
kines_proto-1.0.0.dist-info/top_level.txt
kines_proto-1.0.0.dist-info/RECORD
