Metadata-Version: 2.1
Name: kines-proto
Version: 1.0.0
Summary: Friendly Command Line Interface for Amazon Kinesis Data Streams
Home-page: https://github.com/dinsaw/kines
Author: Dinesh Sawant
Author-email: dineshsawant300@gmail.com
License: UNKNOWN
Platform: UNKNOWN
Classifier: Programming Language :: Python :: 3
Classifier: License :: OSI Approved :: MIT License
Classifier: Operating System :: OS Independent
Requires-Python: >=3.6
Requires-Dist: Click
Requires-Dist: boto3
Requires-Dist: terminaltables
